AUTHORS
MANIFEST.in
README.md
license.txt
setup.cfg
setup.py
django_shop_payer_backend/__init__.py
django_shop_payer_backend/apps.py
django_shop_payer_backend/backends.py
django_shop_payer_backend/forms.py
django_shop_payer_backend/helper.py
django_shop_payer_backend/models.py
django_shop_payer_backend/tests.py
django_shop_payer_backend.egg-info/PKG-INFO
django_shop_payer_backend.egg-info/SOURCES.txt
django_shop_payer_backend.egg-info/dependency_links.txt
django_shop_payer_backend.egg-info/requires.txt
django_shop_payer_backend.egg-info/top_level.txt
django_shop_payer_backend/locale/sv/LC_MESSAGES/django.mo
django_shop_payer_backend/locale/sv/LC_MESSAGES/django.po
django_shop_payer_backend/templates/payer_backend/redirect-content.html
django_shop_payer_backend/templates/payer_backend/redirect.html