Metadata-Version: 1.1
Name: django-shop-payer-backend
Version: 0.1.5
Summary: Payment backend for django SHOP and Payer.
Home-page: https://github.com/dessibelle/django-shop-payer-backend
Author: Simon Fransson
Author-email: simon@dessibelle.se
License: MIT
Download-URL: https://github.com/dessibelle/django-shop-payer-backend/archive/0.1.5.tar.gz
Platform: UNKNOWN
Classifier: Intended Audience :: Developers
Classifier: License :: OSI Approved :: MIT License
Classifier: Operating System :: OS Independent
Classifier: Topic :: Software Development
